{
  "basics": {
    "name": "Isabelle Castro",
    "label": "Student",
    "picture": "https://github.com/icastro808.png",
    "email": "icastro@hawaii.edu",
    "phone": "808-347-9212",
    "website": "https://icastro808.github.io",
    "summary": "I am a student at the University of Hawaii at Manoa pursuing a B.S. in Computer Science. I expect to graduate Spring, 2026.",
    "location": { "address": "", "postalCode": "96707", "city": "Kapolei", "countryCode": "USA", "region": "Hawaii" },
    "profiles": [
      { "network": "github", "username": "icastro808", "url": "http://github.com/icastro808" },
      { "network": "linkedin", "username": "icastro808", "url": "https://www.linkedin.com/in/isabelle-castro-19358a326/" }
    ]
  },
  "interests": [
    { "name": "Software Development" },
    { "name": "Game Development" },
    { "name": "Astronomy" },
    { "name": "Traveling" }
  ],
  "skills": [
    {
      "name": "Languages and Frameworks",
      "keywords": [ "C", "C++", "Java", "JavaScript", "TypeScript", "Python" ]
    },
    {
      "name": "Toolsets/OS",
      "keywords": [ "MacOS", "Git/GitHub", "Visual Studio Code", "Eclipse", "IntelliJ" ]
    }
  ],
  "education": [
    {
      "institution": "University of Hawaii, Honolulu, HI",
      "area": "Computer Science (expected Spring, 2026)",
      "studyType": "B.S.",
      "startDate": "2024-08-26",
      "endDate": "Present",
      "courses": [
      ]
    }
  ],
  "work": [
    {
      "company": "Leeward Community College",
      "position": "Computer Science Tutor",
      "website": "https://www.leeward.hawaii.edu/tutoring",
      "startDate": "2023-01-24",
      "endDate": "Present",
      "summary": "Provide tutoring services for UH students taking ICS 101 / 110P / 111 / 211 / 212",
      "highlights": [
        "Assist students in Java, Python, C, C++, and Microsoft Excel",
        "Communicate complex programming concepts clearly, adapting to students' skill levels to enhance understanding",
        "Manage time effectively by balancing tutoring duties with academic coursework and deadlines",
        "Maintain and organize tutoring data and records using Microsoft Excel, ensuring smooth administrative operations",
        "Meet with and discuss student improvement with Computer Science professors"
      ]
    }
  ],
  "references": [
    {
      "name": "Available upon request"
    }
  ]
}
